falcon_heavy/__init__.py
falcon_heavy/utils.py
falcon_heavy/version.py
falcon_heavy/contrib/__init__.py
falcon_heavy/contrib/decorators.py
falcon_heavy/contrib/name_resolver.py
falcon_heavy/contrib/operations.py
falcon_heavy/contrib/parsers.py
falcon_heavy/contrib/path.py
falcon_heavy/contrib/renderers.py
falcon_heavy/contrib/request.py
falcon_heavy/contrib/responses.py
falcon_heavy/contrib/utils.py
falcon_heavy/contrib/django/__init__.py
falcon_heavy/contrib/django/decorators.py
falcon_heavy/contrib/django/routing.py
falcon_heavy/contrib/falcon/__init__.py
falcon_heavy/contrib/falcon/decorators.py
falcon_heavy/contrib/falcon/testing.py
falcon_heavy/contrib/flask/__init__.py
falcon_heavy/contrib/flask/decorators.py
falcon_heavy/contrib/flask/routing.py
falcon_heavy/core/__init__.py
falcon_heavy/core/context.py
falcon_heavy/core/encoders.py
falcon_heavy/core/utils.py
falcon_heavy/core/factories/__init__.py
falcon_heavy/core/factories/common.py
falcon_heavy/core/factories/content.py
falcon_heavy/core/factories/datastructures.py
falcon_heavy/core/factories/headers.py
falcon_heavy/core/factories/media_handlers.py
falcon_heavy/core/factories/media_type.py
falcon_heavy/core/factories/parameter_styles.py
falcon_heavy/core/factories/parameters.py
falcon_heavy/core/factories/registry.py
falcon_heavy/core/factories/request.py
falcon_heavy/core/factories/request_body.py
falcon_heavy/core/factories/response.py
falcon_heavy/core/factories/responses.py
falcon_heavy/core/factories/type.py
falcon_heavy/core/factories/utils.py
falcon_heavy/core/openapi/__init__.py
falcon_heavy/core/openapi/base.py
falcon_heavy/core/openapi/callback.py
falcon_heavy/core/openapi/components.py
falcon_heavy/core/openapi/constants.py
falcon_heavy/core/openapi/contact.py
falcon_heavy/core/openapi/discriminator.py
falcon_heavy/core/openapi/encoding.py
falcon_heavy/core/openapi/example.py
falcon_heavy/core/openapi/external_documentation.py
falcon_heavy/core/openapi/header.py
falcon_heavy-0.1.2.dist-info/LICENSE
falcon_heavy-0.1.2.dist-info/METADATA
falcon_heavy-0.1.2.dist-info/WHEEL
falcon_heavy-0.1.2.dist-info/top_level.txt
falcon_heavy-0.1.2.dist-info/RECORD
